encodingutils/__init__.py
encodingutils/char.py
encodingutils/codepages.py
encodingutils/testencoding.py
encodingutils/udat2dictkeys.py
strescpos/__init__.py
strescpos/esc.py
uni2esky/__init__.py
uni2esky/dat.py
uni2esky/eskymap.py
uni2esky/list_chars.py
uni2esky/rand.py
uni2esky/regen_map.py
uni2esky/uni2esky.py
uni2esky/user_def.py
uni2esky-1.0.9.dist-info/DESCRIPTION.rst
uni2esky-1.0.9.dist-info/METADATA
uni2esky-1.0.9.dist-info/RECORD
uni2esky-1.0.9.dist-info/WHEEL
uni2esky-1.0.9.dist-info/entry_points.txt
uni2esky-1.0.9.dist-info/metadata.json
uni2esky-1.0.9.dist-info/top_level.txt
